requirements.txt
setup.py
django_configurations_apps/__init__.py
django_configurations_apps.egg-info/PKG-INFO
django_configurations_apps.egg-info/SOURCES.txt
django_configurations_apps.egg-info/dependency_links.txt
django_configurations_apps.egg-info/requires.txt
django_configurations_apps.egg-info/top_level.txt