Metadata-Version: 2.1
Name: django-configurations-apps
Version: 2020.7.2
Summary: django-configurations apps settings
Home-page: https://github.com/andrewp-as-is/django-configurations-apps.py
License: Unlicense
Keywords: django django-configurations apps
Platform: UNKNOWN
Classifier: Framework :: Django
Classifier: License :: Public Domain
Classifier: Operating System :: OS Independent
Classifier: Programming Language :: Python :: 3
